{
    "business_name":  "NYU Langone Fertility Center",
    "domain":  "fertilityny.org",
    "site_title":  "NYC\u0027s Leading IVF Clinics | NYU Langone Fertility Center",
    "meta_description":  "",
    "offer_summary":  "Title: NYC\u0027s Leading IVF Clinics | NYU Langone Fertility Center",
    "offer_lines":  [
                        "Title: NYC\u0027s Leading IVF Clinics | NYU Langone Fertility Center",
                        "NYC\u0027s Leading IVF Clinics | NYU Langone Fertility Center",
                        "[Skip To Content](http://fertilityny.org/#main)",
                        "[Castle Connolly has recognized six of our New York City fertility specialists as 2026 Top Doctors!](https://www.fertilityny.org/blog/six-nyulfc-physicians-named-castle-connolly-top-doctors-2026)",
                        "[![Image 1: NYU Langone Fertility Center™ Homepage](http://fertilityny.org/images/logo.svg)![Image 2: NYU Langone Fertility Center™ Homepage](http://fertilityny.org/images/logo-scroll.svg)](http://fertilityny.org/)",
                        "*   [Patient Portal](https://fertilitycenterportal.com/#/Login)",
                        "*   [LGBTQ+](http://fertilityny.org/fertility-treatment/lgbtq-fertility-treatment)",
                        "*   [Locations](http://fertilityny.org/our-fertility-clinics)"
                    ],
    "pain_points":  [
                        "From your first consultation to your first congratulations, we\u0027re here to support you with outstanding family-building options.",
                        "Supporting all couples and individuals on their journey to parenthood.",
                        "*   [![Image 10: Stress Reduction Tips](http://fertilityny.org/) ### Stress Reduction Tips](https://www.preludefertility.com/coping-strategies)",
                        "*   [![Image 17](http://fertilityny.org/)February 20, 2026 ### Pregnancy Confirmation: What Comes Next for You and Your Baby Finding out you’re pregnant is one of life’s biggest moments — whether you’ve been trying for a while or this is brand-new territory.",
                        "*   [![Image 18](http://fertilityny.org/)February 2, 2026 ### Staying Active While Trying to Conceive: Fertility Treatment Exercise Tips Balancing fertility treatment with the rest of your life — work, commuting, workouts — can feel like a juggling act.",
                        "Good news: for most people, staying active while trying to conceive ..."
                    ],
    "authority_proof":  [
                            "Title: NYC\u0027s Leading IVF Clinics | NYU Langone Fertility Center",
                            "NYC\u0027s Leading IVF Clinics | NYU Langone Fertility Center",
                            "*   [Success at NYU](https://www.fertilityny.org/success-at-nyu)",
                            "Through world-class science and care, our New York City fertility clinics help people have healthy babies, when they\u0027re ready.",
                            "Join the thousands of patients who\u0027ve placed their trust in our experts to deliver outstanding clinical outcomes – with efficiency, transparency, and personalization.",
                            "*   ![Image 4: 175+ Years of Combined Experience](http://fertilityny.org/)"
                        ],
    "testimonials":  [
                         "I truly felt that we came up with our fertility plan together, which helped make me feel more involved and in control.",
                         "I am writing this review pregnant, and it is all thanks to Dr. DeVore. I switched to NYU after having a negative experience at a previous clinic where I was informed there was zero chance I would conceive."
                     ],
    "prices":  [

               ],
    "target_audience":  "Future family planners and patients considering IVF or egg freezing",
    "voice":  "Clinical, evidence-led, and authoritative",
    "logo_url":  "https://fertilityny.org/images/logo.svg",
    "hero_image_url":  "https://cdn.buttercms.com/IbHJwDf0QDqqGR37weZw",
    "social_links":  [
                         "https://www.instagram.com/fertility_ny/",
                         "https://www.instagram.com/fertility_ny/\\"
                     ],
    "brand_primary":  "#0B0B0B",
    "brand_secondary":  "#580F8B",
    "brand_bg":  "#F7FAFC",
    "brand_white":  "#FFFFFF",
    "brand_text":  "#1B1E23",
    "heading_font":  "Roboto",
    "body_font":  "Caslon",
    "scraping_mode":  "direct"
}
